pysovryn/__init__.py
pysovryn/core.py
pysovryn-0.1.dist-info/LICENSE
pysovryn-0.1.dist-info/METADATA
pysovryn-0.1.dist-info/WHEEL
pysovryn-0.1.dist-info/top_level.txt
pysovryn-0.1.dist-info/RECORD
