Metadata-Version: 2.1
Name: pysovryn
Version: 0.1
Summary: UNKNOWN
Home-page: UNKNOWN
Author: Jamiel Sheikh
Author-email: UNKNOWN
License: UNKNOWN
Platform: UNKNOWN
Requires-Dist: matplotlib
Requires-Dist: web3
Requires-Dist: pandas
Requires-Dist: datetime
Requires-Dist: requests
